[{"params":{"stateId":"vukovarsko-srijemska","cityId":"privlaka"}},{"params":{"stateId":"osjecko-baranjska","cityId":"donji-miholjac"}},{"params":{"stateId":"vukovarsko-srijemska","cityId":"vukovar"}},{"params":{"stateId":"medimurska","cityId":"cakovec"}},{"params":{"stateId":"grad-zagreb","cityId":"podsljeme"}},{"params":{"stateId":"medimurska","cityId":"nedelisce"}},{"params":{"stateId":"primorsko-goranska","cityId":"ravna-gora"}},{"params":{"stateId":"istarska","cityId":"funtana"}},{"params":{"stateId":"istra","cityId":"porec"}},{"params":{"stateId":"sisacko-moslavacka","cityId":"sisak-okolica"}},{"params":{"stateId":"splitsko-dalmatinska","cityId":"jelsa"}},{"params":{"stateId":"zadarska","cityId":"zadar"}},{"params":{"stateId":"sibensko-kninska","cityId":"pirovac"}},{"params":{"stateId":"varazdinska","cityId":"ludbreg"}},{"params":{"stateId":"sisacko-moslavacka","cityId":"petrinja"}},{"params":{"stateId":"primorsko-goranska","cityId":"bakar"}},{"params":{"stateId":"krapinsko-zagorska","cityId":"tuhelj"}},{"params":{"stateId":"brodsko-posavska","cityId":"oriovac"}},{"params":{"stateId":"splitsko-dalmatinska","cityId":"dugopolje"}},{"params":{"stateId":"zagrebacka","cityId":"jastrebarsko-okolica"}},{"params":{"stateId":"krapinsko-zagorska","cityId":"kumrovec"}},{"params":{"stateId":"zagrebacka","cityId":"samobor"}},{"params":{"stateId":"istarska","cityId":"fazana"}},{"params":{"stateId":"karlovacka","cityId":"ogulin"}},{"params":{"stateId":"primorsko-goranska","cityId":"rijeka"}},{"params":{"stateId":"istarska","cityId":"kanfanar"}},{"params":{"stateId":"grad-zagreb","cityId":"crnomerec"}},{"params":{"stateId":"primorsko-goranska","cityId":"omisalj"}},{"params":{"stateId":"krapinsko-zagorska","cityId":"klanjec"}},{"params":{"stateId":"sibensko-kninska","cityId":"skradin"}},{"params":{"stateId":"zadarska","cityId":"policnik"}},{"params":{"stateId":"krapinsko-zagorska","cityId":"zabok"}},{"params":{"stateId":"splitsko-dalmatinska","cityId":"pucisca"}},{"params":{"stateId":"medimurska","cityId":"cakovec-okolica"}},{"params":{"stateId":"splitsko-dalmatinska","cityId":"milna"}},{"params":{"stateId":"viroviticko-podravska","cityId":"zdenci"}},{"params":{"stateId":"zadarska","cityId":"gracac"}},{"params":{"stateId":"medimurska","cityId":"prelog"}},{"params":{"stateId":"primorsko-goranska","cityId":"opatija-okolica"}},{"params":{"stateId":"zadarska","cityId":"preko"}},{"params":{"stateId":"splitsko-dalmatinska","cityId":"vis"}},{"params":{"stateId":"splitsko-dalmatinska","cityId":"sucuraj"}},{"params":{"stateId":"zagrebacka","cityId":"rugvica"}},{"params":{"stateId":"dubrovacko-neretvanska","cityId":"ston"}},{"params":{"stateId":"splitsko-dalmatinska","cityId":"otok"}},{"params":{"stateId":"sisacko-moslavacka","cityId":"velika-ludina"}},{"params":{"stateId":"sibensko-kninska","cityId":"knin"}},{"params":{"stateId":"istarska","cityId":"rasa"}},{"params":{"stateId":"brodsko-posavska","cityId":"slavonski-brod"}},{"params":{"stateId":"primorsko-goranska","cityId":"cavle"}},{"params":{"stateId":"sibensko-kninska","cityId":"vodice"}},{"params":{"stateId":"zadarska","cityId":"kolan"}},{"params":{"stateId":"primorsko-goranska","cityId":"delnice"}},{"params":{"stateId":"sibensko-kninska","cityId":"rogoznica"}},{"params":{"stateId":"zagrebacka","cityId":"jastrebarsko"}},{"params":{"stateId":"sisacko-moslavacka","cityId":"topusko"}},{"params":{"stateId":"karlovacka","cityId":"draganic"}},{"params":{"stateId":"licko-senjska","cityId":"gospic"}},{"params":{"stateId":"zagrebacka","cityId":"velika-gorica"}},{"params":{"stateId":"osjecko-baranjska","cityId":"osijek"}},{"params":{"stateId":"krapinsko-zagorska","cityId":"stubicke-toplice"}},{"params":{"stateId":"dubrovacko-neretvanska","cityId":"konavle"}},{"params":{"stateId":"dubrovacko-neretvanska","cityId":"ploce"}},{"params":{"stateId":"zadarska","cityId":"vrsi"}},{"params":{"stateId":"sibensko-kninska","cityId":"murter"}},{"params":{"stateId":"istarska","cityId":"svetvincenat"}},{"params":{"stateId":"istarska","cityId":"pazin"}},{"params":{"stateId":"istarska","cityId":"porec"}},{"params":{"stateId":"medimurska","cityId":"kotoriba"}},{"params":{"stateId":"osjecko-baranjska","cityId":"popovac"}},{"params":{"stateId":"splitsko-dalmatinska","cityId":"prgomet"}},{"params":{"stateId":"istra","cityId":"marcana"}},{"params":{"stateId":"zagrebacka","cityId":"sveti-ivan-zelina"}},{"params":{"stateId":"splitsko-dalmatinska","cityId":"hvar"}},{"params":{"stateId":"zagrebacka","cityId":"dugo-selo"}},{"params":{"stateId":"zadarska","cityId":"kukljica"}},{"params":{"stateId":"koprivnicko-krizevacka","cityId":"krizevci"}},{"params":{"stateId":"krapinsko-zagorska","cityId":"bedekovcina"}},{"params":{"stateId":"istarska","cityId":"sveti-petar-u-sumi"}},{"params":{"stateId":"karlovacka","cityId":"karlovac"}},{"params":{"stateId":"grad-zagreb","cityId":"tresnjevka-sjever"}},{"params":{"stateId":"splitsko-dalmatinska","cityId":"tucepi"}},{"params":{"stateId":"istarska","cityId":"lupoglav"}},{"params":{"stateId":"dubrovacko-neretvanska","cityId":"dubrovacko-primorje"}},{"params":{"stateId":"splitsko-dalmatinska","cityId":"brela"}},{"params":{"stateId":"licko-senjska","cityId":"novalja"}},{"params":{"stateId":"koprivnicko-krizevacka","cityId":"koprivnica"}},{"params":{"stateId":"istarska","cityId":"marcana"}},{"params":{"stateId":"koprivnicko-krizevacka","cityId":"sveti-ivan-zabno"}},{"params":{"stateId":"grad-zagreb","cityId":"pescenica-zitnjak"}},{"params":{"stateId":"varazdinska","cityId":"varazdin"}},{"params":{"stateId":"istarska","cityId":"tinjan"}},{"params":{"stateId":"varazdinska","cityId":"bednja"}},{"params":{"stateId":"primorsko-goranska","cityId":"crikvenica"}},{"params":{"stateId":"vukovarsko-srijemska","cityId":"zupanja"}},{"params":{"stateId":"vukovarsko-srijemska","cityId":"ilok"}},{"params":{"stateId":"dubrovacko-neretvanska","cityId":"trpanj"}},{"params":{"stateId":"krapinsko-zagorska","cityId":"durmanec"}},{"params":{"stateId":"zadarska","cityId":"sukosan"}},{"params":{"stateId":"varazdinska","cityId":"sracinec"}},{"params":{"stateId":"medimurska","cityId":"sveti-juraj-na-bregu"}},{"params":{"stateId":"licko-senjska","cityId":"brinje"}},{"params":{"stateId":"grad-zagreb","cityId":"novi-zagreb-zapad"}},{"params":{"stateId":"primorsko-goranska","cityId":"moscenicka-draga"}},{"params":{"stateId":"bjelovarsko-bilogorska","cityId":"grubisno-polje"}},{"params":{"stateId":"zadarska","cityId":"obrovac"}},{"params":{"stateId":"zagrebacka","cityId":"pisarovina"}},{"params":{"stateId":"osjecko-baranjska","cityId":"nasice"}},{"params":{"stateId":"zagrebacka","cityId":"pokupsko"}},{"params":{"stateId":"sibensko-kninska","cityId":"tribunj"}},{"params":{"stateId":"zadarska","cityId":"sali"}},{"params":{"stateId":"krapinsko-zagorska","cityId":"konjscina"}},{"params":{"stateId":"splitsko-dalmatinska","cityId":"sinj"}},{"params":{"stateId":"istarska","cityId":"krsan"}},{"params":{"stateId":"varazdinska","cityId":"marusevec"}},{"params":{"stateId":"splitsko-dalmatinska","cityId":"solin"}},{"params":{"stateId":"varazdinska","cityId":"gornji-kneginec"}},{"params":{"stateId":"dubrovacko-neretvanska","cityId":"orebic"}},{"params":{"stateId":"primorsko-goranska","cityId":"cabar"}},{"params":{"stateId":"varazdinska","cityId":"cestica"}},{"params":{"stateId":"vukovarsko-srijemska","cityId":"vinkovci"}},{"params":{"stateId":"splitsko-dalmatinska","cityId":"trogir-okolica"}},{"params":{"stateId":"vukovarsko-srijemska","cityId":"bosnjaci"}},{"params":{"stateId":"splitsko-dalmatinska","cityId":"trilj"}},{"params":{"stateId":"varazdinska","cityId":"veliki-bukovec"}},{"params":{"stateId":"dubrovacko-neretvanska","cityId":"mljet"}},{"params":{"stateId":"bjelovarsko-bilogorska","cityId":"daruvar"}},{"params":{"stateId":"sibensko-kninska","cityId":"sibenik-okolica"}},{"params":{"stateId":"istra","cityId":"umag"}},{"params":{"stateId":"dubrovacko-neretvanska","cityId":"metkovic"}},{"params":{"stateId":"krapinsko-zagorska","cityId":"krapinske-toplice"}},{"params":{"stateId":"dubrovacko-neretvanska","cityId":"opuzen"}},{"params":{"stateId":"zadarska","cityId":"jasenice"}},{"params":{"stateId":"bjelovarsko-bilogorska","cityId":"garesnica"}},{"params":{"stateId":"bjelovarsko-bilogorska","cityId":"veliki-grdevac"}},{"params":{"stateId":"zagrebacka","cityId":"samobor-okolica"}},{"params":{"stateId":"zadarska","cityId":"bibinje"}},{"params":{"stateId":"zagrebacka","cityId":"krasic"}},{"params":{"stateId":"krapinsko-zagorska","cityId":"hum-na-sutli"}},{"params":{"stateId":"splitsko-dalmatinska","cityId":"podgora"}},{"params":{"stateId":"sisacko-moslavacka","cityId":"popovaca"}},{"params":{"stateId":"istarska","cityId":"motovun"}},{"params":{"stateId":"sisacko-moslavacka","cityId":"sisak"}},{"params":{"stateId":"licko-senjska","cityId":"gospic-okolica"}},{"params":{"stateId":"splitsko-dalmatinska","cityId":"stari-grad"}},{"params":{"stateId":"medimurska","cityId":"strigova"}},{"params":{"stateId":"zadarska","cityId":"benkovac"}},{"params":{"stateId":"primorsko-goranska","cityId":"matulji"}},{"params":{"stateId":"osjecko-baranjska","cityId":"koska"}},{"params":{"stateId":"karlovacka","cityId":"ribnik"}},{"params":{"stateId":"splitsko-dalmatinska","cityId":"split-okolica"}},{"params":{"stateId":"medimurska","cityId":"donja-dubrava"}},{"params":{"stateId":"bjelovarsko-bilogorska","cityId":"bjelovar"}},{"params":{"stateId":"zagrebacka","cityId":"ivanic-grad-okolica"}},{"params":{"stateId":"varazdinska","cityId":"sveti-ilija"}},{"params":{"stateId":"sisacko-moslavacka","cityId":"novska"}},{"params":{"stateId":"zadarska","cityId":"povljana"}},{"params":{"stateId":"bjelovarsko-bilogorska","cityId":"cazma"}},{"params":{"stateId":"istarska","cityId":"tar-vabriga"}},{"params":{"stateId":"karlovacka","cityId":"ozalj"}},{"params":{"stateId":"varazdinska","cityId":"martijanec"}},{"params":{"stateId":"sibensko-kninska","cityId":"primosten"}},{"params":{"stateId":"dubrovacko-neretvanska","cityId":"lumbarda"}},{"params":{"stateId":"primorsko-goranska","cityId":"jelenje"}},{"params":{"stateId":"istarska","cityId":"liznjan"}},{"params":{"stateId":"primorsko-goranska","cityId":"vrbnik"}},{"params":{"stateId":"brodsko-posavska","cityId":"okucani"}},{"params":{"stateId":"licko-senjska","cityId":"udbina"}},{"params":{"stateId":"grad-zagreb","cityId":"podsused-vrapce"}},{"params":{"stateId":"primorsko-goranska","cityId":"vrbovsko"}},{"params":{"stateId":"zagrebacka","cityId":"klostar-ivanic"}},{"params":{"stateId":"krapinsko-zagorska","cityId":"krapina-okolica"}},{"params":{"stateId":"bjelovarsko-bilogorska","cityId":"koncanica"}},{"params":{"stateId":"koprivnicko-krizevacka","cityId":"peteranec"}},{"params":{"stateId":"grad-zagreb","cityId":"zagreb-okolica"}},{"params":{"stateId":"licko-senjska","cityId":"karlobag"}},{"params":{"stateId":"zagrebacka","cityId":"brdovec"}},{"params":{"stateId":"karlovacka","cityId":"vojnic"}},{"params":{"stateId":"istra","cityId":"vodnjan"}},{"params":{"stateId":"zadarska","cityId":"pag"}},{"params":{"stateId":"bjelovarsko-bilogorska","cityId":"sandrovac"}},{"params":{"stateId":"istarska","cityId":"zminj"}},{"params":{"stateId":"licko-senjska","cityId":"senj"}},{"params":{"stateId":"sibensko-kninska","cityId":"drnis"}},{"params":{"stateId":"primorsko-goranska","cityId":"baska"}},{"params":{"stateId":"splitsko-dalmatinska","cityId":"split"}},{"params":{"stateId":"krapinsko-zagorska","cityId":"zlatar-bistrica"}},{"params":{"stateId":"istarska","cityId":"buje"}},{"params":{"stateId":"licko-senjska","cityId":"otocac"}},{"params":{"stateId":"grad-zagreb","cityId":"donji-grad"}},{"params":{"stateId":"dubrovacko-neretvanska","cityId":"dubrovnik"}},{"params":{"stateId":"splitsko-dalmatinska","cityId":"bol"}},{"params":{"stateId":"zagrebacka","cityId":"dugo-selo-okolica"}},{"params":{"stateId":"istra","cityId":"liznjan"}},{"params":{"stateId":"dubrovacko-neretvanska","cityId":"zupa-dubrovacka"}},{"params":{"stateId":"primorsko-goranska","cityId":"fuzine"}},{"params":{"stateId":"sibensko-kninska","cityId":"tisno"}},{"params":{"stateId":"pozesko-slavonska","cityId":"pozega"}},{"params":{"stateId":"grad-zagreb","cityId":"maksimir"}},{"params":{"stateId":"osjecko-baranjska","cityId":"ceminac"}},{"params":{"stateId":"krapinsko-zagorska","cityId":"donja-stubica"}},{"params":{"stateId":"splitsko-dalmatinska","cityId":"omis"}},{"params":{"stateId":"krapinsko-zagorska","cityId":"krapina"}},{"params":{"stateId":"primorsko-goranska","cityId":"kostrena"}},{"params":{"stateId":"primorsko-goranska","cityId":"lokve"}},{"params":{"stateId":"bjelovarsko-bilogorska","cityId":"sirac"}},{"params":{"stateId":"istarska","cityId":"labin"}},{"params":{"stateId":"zadarska","cityId":"biograd-na-moru"}},{"params":{"stateId":"varazdinska","cityId":"trnovec-bartolovecki"}},{"params":{"stateId":"istarska","cityId":"pula"}},{"params":{"stateId":"koprivnicko-krizevacka","cityId":"novigrad-podravski"}},{"params":{"stateId":"bjelovarsko-bilogorska","cityId":"bjelovar-okolica"}},{"params":{"stateId":"zadarska","cityId":"pakostane"}},{"params":{"stateId":"osjecko-baranjska","cityId":"erdut"}},{"params":{"stateId":"karlovacka","cityId":"karlovac-okolica"}},{"params":{"stateId":"zadarska","cityId":"starigrad"}},{"params":{"stateId":"osjecko-baranjska","cityId":"viskovci"}},{"params":{"stateId":"zadarska","cityId":"zadar-okolica"}},{"params":{}},{"params":{"stateId":"splitsko-dalmatinska","cityId":"sestanovac"}},{"params":{"stateId":"karlovacka","cityId":"slunj"}},{"params":{"stateId":"koprivnicko-krizevacka","cityId":"molve"}},{"params":{"stateId":"grad-zagreb","cityId":"gornji-grad-medvescak"}},{"params":{"stateId":"brodsko-posavska","cityId":"nova-gradiska"}},{"params":{"stateId":"licko-senjska","cityId":"plitvicka-jezera"}},{"params":{"stateId":"varazdinska","cityId":"vinica"}},{"params":{"stateId":"primorsko-goranska","cityId":"mali-losinj"}},{"params":{"stateId":"primorsko-goranska","cityId":"opatija"}},{"params":{"stateId":"splitsko-dalmatinska","cityId":"imotski"}},{"params":{"stateId":"osjecko-baranjska","cityId":"darda"}},{"params":{"stateId":"istarska","cityId":"brtonigla"}},{"params":{"stateId":"medimurska","cityId":"senkovec"}},{"params":{"stateId":"splitsko-dalmatinska","cityId":"kastela"}},{"params":{"stateId":"zagrebacka","cityId":"ivanic-grad"}},{"params":{"stateId":"primorsko-goranska","cityId":"mrkopalj"}},{"params":{"stateId":"istra","cityId":"rovinj"}},{"params":{"stateId":"splitsko-dalmatinska","cityId":"okrug"}},{"params":{"stateId":"zagrebacka","cityId":"velika-gorica-okolica"}},{"params":{"stateId":"koprivnicko-krizevacka","cityId":"durdevac"}},{"params":{"stateId":"splitsko-dalmatinska","cityId":"solta"}},{"params":{"stateId":"osjecko-baranjska","cityId":"antunovac"}},{"params":{"stateId":"istarska","cityId":"medulin"}},{"params":{"stateId":"istarska","cityId":"oprtalj"}},{"params":{"stateId":"medimurska","cityId":"pribislavec"}},{"params":{"stateId":"primorsko-goranska","cityId":"krk"}},{"params":{"stateId":"osjecko-baranjska","cityId":"beli-manastir"}},{"params":{"stateId":"primorsko-goranska","cityId":"dobrinj"}},{"params":{"stateId":"medimurska","cityId":"gornji-mihaljevec"}},{"params":{"stateId":"splitsko-dalmatinska","cityId":"baska-voda"}},{"params":{"stateId":"splitsko-dalmatinska","cityId":"solin-okolica"}},{"params":{"stateId":"krapinsko-zagorska","cityId":"gornja-stubica"}},{"params":{"stateId":"koprivnicko-krizevacka","cityId":"delekovec"}},{"params":{"stateId":"dubrovacko-neretvanska","cityId":"korcula"}},{"params":{"stateId":"splitsko-dalmatinska","cityId":"podstrana"}},{"params":{"stateId":"varazdinska","cityId":"ivanec"}},{"params":{"stateId":"koprivnicko-krizevacka","cityId":"koprivnicki-bregi"}},{"params":{"stateId":"zagrebacka","cityId":"stupnik"}},{"params":{"stateId":"zagrebacka","cityId":"bistra"}},{"params":{"stateId":"koprivnicko-krizevacka","cityId":"klostar-podravski"}},{"params":{"stateId":"krapinsko-zagorska","cityId":"veliko-trgovisce"}},{"params":{"stateId":"splitsko-dalmatinska","cityId":"sutivan"}},{"params":{"stateId":"splitsko-dalmatinska","cityId":"supetar"}},{"params":{"stateId":"zagrebacka","cityId":"zapresic"}},{"params":{"stateId":"istarska","cityId":"kastelir-labinci"}},{"params":{"stateId":"primorsko-goranska","cityId":"rab"}},{"params":{"stateId":"dubrovacko-neretvanska","cityId":"dubrovnik-okolica"}},{"params":{"stateId":"istarska","cityId":"novigrad"}},{"params":{"stateId":"primorsko-goranska","cityId":"viskovo"}},{"params":{"stateId":"zagrebacka","cityId":"kriz"}},{"params":{"stateId":"karlovacka","cityId":"duga-resa"}},{"params":{"stateId":"zadarska","cityId":"nin"}},{"params":{"stateId":"zadarska","cityId":"pasman"}},{"params":{"stateId":"viroviticko-podravska","cityId":"slatina"}},{"params":{"stateId":"krapinsko-zagorska","cityId":"pregrada"}},{"params":{"stateId":"viroviticko-podravska","cityId":"pitomaca"}},{"params":{"stateId":"zagrebacka","cityId":"preseka"}},{"params":{"stateId":"sisacko-moslavacka","cityId":"kutina"}},{"params":{"stateId":"medimurska","cityId":"strahoninec"}},{"params":{"stateId":"grad-zagreb","cityId":"trnje"}},{"params":{"stateId":"istarska","cityId":"rovinj"}},{"params":{"stateId":"istarska","cityId":"vrsar"}},{"params":{"stateId":"krapinsko-zagorska","cityId":"oroslavje"}},{"params":{"stateId":"primorsko-goranska","cityId":"lovran"}},{"params":{"stateId":"pozesko-slavonska","cityId":"lipik"}},{"params":{"stateId":"splitsko-dalmatinska","cityId":"trogir"}},{"params":{"stateId":"splitsko-dalmatinska","cityId":"klis"}},{"params":{"stateId":"osjecko-baranjska","cityId":"osijek-okolica"}},{"params":{"stateId":"osjecko-baranjska","cityId":"dakovo"}},{"params":{"stateId":"dubrovacko-neretvanska","cityId":"slivno"}},{"params":{"stateId":"zagrebacka","cityId":"sveta-nedelja"}},{"params":{"stateId":"zadarska","cityId":"posedarje"}},{"params":{"stateId":"istarska","cityId":"vodnjan"}},{"params":{"stateId":"zadarska","cityId":"sveti-filip-i-jakov"}},{"params":{"stateId":"varazdinska","cityId":"varazdinske-toplice"}},{"params":{"stateId":"bjelovarsko-bilogorska","cityId":"velika-trnovitica"}},{"params":{"stateId":"zadarska","cityId":"tkon"}},{"params":{"stateId":"splitsko-dalmatinska","cityId":"vrgorac"}},{"params":{"stateId":"splitsko-dalmatinska","cityId":"makarska"}},{"params":{"stateId":"primorsko-goranska","cityId":"punat"}},{"params":{"stateId":"istarska","cityId":"sveta-nedelja"}},{"params":{"stateId":"sisacko-moslavacka","cityId":"sunja"}},{"params":{"stateId":"koprivnicko-krizevacka","cityId":"virje"}},{"params":{"stateId":"zadarska","cityId":"privlaka"}},{"params":{"stateId":"istra","cityId":"pula"}},{"params":{"stateId":"splitsko-dalmatinska","cityId":"gradac"}},{"params":{"stateId":"krapinsko-zagorska","cityId":"sveti-kriz-zacretje"}},{"params":{"stateId":"zadarska","cityId":"razanac"}},{"params":{"stateId":"zagrebacka","cityId":"kravarsko"}},{"params":{"stateId":"pozesko-slavonska","cityId":"kutjevo"}},{"params":{"stateId":"sisacko-moslavacka","cityId":"glina"}},{"params":{"stateId":"grad-zagreb","cityId":"sesvete"}},{"params":{"stateId":"osjecko-baranjska","cityId":"cepin"}},{"params":{"stateId":"varazdinska","cityId":"visoko"}},{"params":{"stateId":"zagrebacka","cityId":"vrbovec"}},{"params":{"stateId":"medimurska","cityId":"mursko-sredisce"}},{"params":{"stateId":"zagrebacka","cityId":"zapresic-okolica"}},{"params":{"stateId":"istarska","cityId":"bale"}},{"params":{"stateId":"splitsko-dalmatinska","cityId":"postira"}},{"params":{"stateId":"istarska","cityId":"umag"}},{"params":{"stateId":"primorsko-goranska","cityId":"vinodolska-opcina"}},{"params":{"stateId":"grad-zagreb","cityId":"tresnjevka-jug"}},{"params":{"stateId":"primorsko-goranska","cityId":"kraljevica"}},{"params":{"stateId":"viroviticko-podravska","cityId":"virovitica"}},{"params":{"stateId":"zadarska","cityId":"kali"}},{"params":{"stateId":"osjecko-baranjska","cityId":"belisce"}},{"params":{"stateId":"sibensko-kninska","cityId":"sibenik"}},{"params":{"stateId":"splitsko-dalmatinska","cityId":"dugi-rat"}},{"params":{"stateId":"zagrebacka","cityId":"dubrava"}},{"params":{"stateId":"dubrovacko-neretvanska","cityId":"vela-luka"}},{"params":{"stateId":"istra","cityId":"medulin"}},{"params":{"stateId":"bjelovarsko-bilogorska","cityId":"nova-raca"}},{"params":{"stateId":"grad-zagreb","cityId":"stenjevec"}},{"params":{"stateId":"dubrovacko-neretvanska","cityId":"janjina"}},{"params":{"stateId":"primorsko-goranska","cityId":"malinska-dubasnica"}},{"params":{"stateId":"zadarska","cityId":"vir"}},{"params":{"stateId":"varazdinska","cityId":"lepoglava"}},{"params":{"stateId":"zadarska","cityId":"novigrad"}},{"params":{"stateId":"osjecko-baranjska","cityId":"durdenovac"}},{"params":{"stateId":"splitsko-dalmatinska","cityId":"zadvarje"}},{"params":{"stateId":"istra","cityId":"fazana"}},{"params":{"stateId":"primorsko-goranska","cityId":"novi-vinodolski"}},{"params":{"stateId":"primorsko-goranska","cityId":"cres"}},{"params":{"stateId":"osjecko-baranjska","cityId":"draz"}},{"params":{"stateId":"pozesko-slavonska","cityId":"pakrac"}},{"params":{"stateId":"istarska","cityId":"sveti-lovrec"}},{"params":{"stateId":"varazdinska","cityId":"novi-marof"}},{"params":{"stateId":"zagrebacka","cityId":"brckovljani"}},{"params":{"stateId":"istarska","cityId":"buzet"}},{"params":{"stateId":"istarska","cityId":"visnjan"}},{"params":{"stateId":"grad-zagreb","cityId":"gornja-dubrava"}},{"params":{"stateId":"primorsko-goranska","cityId":"kastav"}},{"params":{"stateId":"istra","cityId":"novigrad"}},{"params":{"stateId":"grad-zagreb","cityId":"donja-dubrava"}},{"params":{"stateId":"dubrovacko-neretvanska","cityId":"blato"}},{"params":{"stateId":"osjecko-baranjska","cityId":"valpovo"}},{"params":{"stateId":"grad-zagreb","cityId":"novi-zagreb-istok"}},{"params":{"stateId":"splitsko-dalmatinska","cityId":"seget"}},{"params":{"stateId":"medimurska","cityId":"sveti-martin-na-muri"}},{"params":{"stateId":"krapinsko-zagorska","cityId":"zlatar"}},{"params":{"stateId":"medimurska","cityId":"selnica"}},{"params":{"stateId":"splitsko-dalmatinska","cityId":"marina"}},{"params":{"stateId":"grad-zagreb","cityId":"brezovica"}},{"params":{"stateId":"zagrebacka","cityId":"klinca-sela"}}]